quarkz/__init__.py
quarkz/dtypes.py
quarkz/rsa.py
quarkz/utils.py
quarkz-0.0.2.dist-info/METADATA
quarkz-0.0.2.dist-info/WHEEL
quarkz-0.0.2.dist-info/top_level.txt
quarkz-0.0.2.dist-info/RECORD
