Metadata-Version: 2.1
Name: quarkz
Version: 0.0.2
Summary: An Encryption library
Home-page: https://github.com/quarkz-encryption/Quarkz
Author: tavivia
Author-email: tavian@quarkz-encryption.com
License: MIT
Platform: any
